profiling_tools/__init__.py
profiling_tools/analyze_stats.py
profiling_tools/decorators.py
profiling_tools/profiling_utils.py
profiling_tools-0.0.14.dist-info/LICENSE
profiling_tools-0.0.14.dist-info/METADATA
profiling_tools-0.0.14.dist-info/WHEEL
profiling_tools-0.0.14.dist-info/RECORD
